daeauth.py
django_admin_external_auth-0.1.0.dist-info/METADATA
django_admin_external_auth-0.1.0.dist-info/RECORD
django_admin_external_auth-0.1.0.dist-info/top_level.txt
django_admin_external_auth-0.1.0.dist-info/DESCRIPTION.rst
django_admin_external_auth-0.1.0.dist-info/WHEEL
django_admin_external_auth-0.1.0.dist-info/metadata.json
