Metadata-Version: 2.0
Name: django-admin-external-auth
Version: 0.1.0
Summary: Use your Django project's existing authentication views in the admin interface.
Home-page: https://github.com/TaymonB/django-admin-external-auth
Author: Taymon A. Beal
Author-email: taymonbeal@gmail.com
License: MIT
Keywords: admin authentication django
Platform: OS Independent
Classifier: Development Status :: 3 - Alpha
Classifier: Environment :: Web Environment
Classifier: Framework :: Django
Classifier: Intended Audience :: Developers
Classifier: License :: OSI Approved :: MIT License
Classifier: Operating System :: OS Independent
Classifier: Programming Language :: Python :: 2
Classifier: Programming Language :: Python :: 2.7
Classifier: Programming Language :: Python :: 3
Classifier: Programming Language :: Python :: 3.2
Classifier: Programming Language :: Python :: 3.3
Classifier: Programming Language :: Python :: 3.4
Classifier: Topic :: Software Development :: Libraries :: Python Modules
Requires-Dist: Django (>=1.7)
